Metadata-Version: 2.1
Name: sostupid
Version: 0.0.1
Summary: Sus Math Library For Cavemen
Home-page: UNKNOWN
Author: Daniel Borro
Author-email: 
License: MIT
Platform: UNKNOWN
Classifier: Operating System :: Microsoft :: Windows :: Windows 10
Classifier: License :: OSI Approved :: MIT License
Classifier: Programming Language :: Python
License-File: LICENSE.txt
